debabelizer-0.2.5.dist-info/METADATA
debabelizer-0.2.5.dist-info/WHEEL
debabelizer.libs/libcrypto-d0003de0.so.3
debabelizer.libs/libssl-2ffb22b1.so.3
debabelizer.libs/libzstd-17b6900d.so.1
debabelizer/__init__.py
debabelizer/__pycache__/__init__.cpython-312.pyc
debabelizer/_internal.abi3.so
debabelizer-0.2.5.dist-info/RECORD
