Metadata-Version: 2.4
Name: debabelizer
Version: 0.2.5
Classifier: Development Status :: 7 - Inactive
Classifier: Intended Audience :: Developers
Classifier: License :: OSI Approved :: MIT License
Classifier: Operating System :: OS Independent
Classifier: Programming Language :: Python :: 3
Classifier: Programming Language :: Python :: 3.8
Classifier: Programming Language :: Python :: 3.9
Classifier: Programming Language :: Python :: 3.10
Classifier: Programming Language :: Python :: 3.11
Classifier: Programming Language :: Python :: 3.12
Classifier: Programming Language :: Rust
Classifier: Topic :: Multimedia :: Sound/Audio :: Speech
Classifier: Topic :: Software Development :: Libraries :: Python Modules
Requires-Dist: pytest>=7.0 ; extra == 'dev'
Requires-Dist: pytest-asyncio>=0.21.0 ; extra == 'dev'
Requires-Dist: black>=22.0 ; extra == 'dev'
Requires-Dist: ruff>=0.1.0 ; extra == 'dev'
Provides-Extra: dev
Summary: DEPRECATED - This package is no longer maintained. Neither the Python nor Rust implementations are production-ready.
Keywords: speech,text-to-speech,speech-to-text,voice,audio
Author-email: Debabelizer Contributors <contributors@debabelizer.com>
Requires-Python: >=3.8
Project-URL: Homepage, https://github.com/debabelizer/debabelizer
Project-URL: Documentation, https://docs.debabelizer.com
Project-URL: Repository, https://github.com/debabelizer/debabelizer.git
Project-URL: Bug Tracker, https://github.com/debabelizer/debabelizer/issues
